flake8_helper.pth
flake8_helper/__init__.py
flake8_helper/py.typed
flake8_helper-0.2.0.dist-info/METADATA
flake8_helper-0.2.0.dist-info/LICENSE
flake8_helper-0.2.0.dist-info/WHEEL
flake8_helper-0.2.0.dist-info/entry_points.txt
flake8_helper-0.2.0.dist-info/top_level.txt
flake8_helper-0.2.0.dist-info/RECORD
