Metadata-Version: 2.1
Name: flake8-helper
Version: 0.2.0
Summary: A helper library for Flake8 plugins.
Author-email: Dominic Davis-Foster <dominic@davis-foster.co.uk>
License: MIT
Keywords: flake8
Home-page: https://github.com/python-formate/flake8-helper
Project-URL: Issue Tracker, https://github.com/python-formate/flake8-helper/issues
Project-URL: Source Code, https://github.com/python-formate/flake8-helper
Project-URL: Documentation, https://flake8-helper.readthedocs.io/en/latest
Platform: Windows
Platform: macOS
Platform: Linux
Classifier: Development Status :: 4 - Beta
Classifier: Framework :: Flake8
Classifier: Intended Audience :: Developers
Classifier: License :: OSI Approved :: MIT License
Classifier: Operating System :: OS Independent
Classifier: Programming Language :: Python
Classifier: Programming Language :: Python :: 3 :: Only
Classifier: Programming Language :: Python :: 3.6
Classifier: Programming Language :: Python :: 3.7
Classifier: Programming Language :: Python :: 3.8
Classifier: Programming Language :: Python :: 3.9
Classifier: Programming Language :: Python :: Implementation :: CPython
Classifier: Programming Language :: Python :: Implementation :: PyPy
Classifier: Topic :: Utilities
Classifier: Typing :: Typed
Requires-Python: >=3.6
Requires-Dist: flake8>=3.8.4
